{
    "मूरत मधुर मनोहर": [
        "slokas/brahm jeev maya/Brahm Jeev Maya Kya Hai 22 [Kot3Rv9_U-E]/ramayan मूरत मधुर मनोहर.mp3"
    ],
    "इन्हहि बिलोकत अति": [
        "slokas/brahm jeev maya/Brahm Jeev Maya Kya Hai 22 [Kot3Rv9_U-E]/ramayan इन्हहि बिलोकत अति.mp3"
    ],
    "सहज बिराग रूप": [
        "slokas/brahm jeev maya/Brahm Jeev Maya Kya Hai 22 [Kot3Rv9_U-E]/ramayan सहज बिराग रूप.mp3"
    ],
    "जाकी रही": [
        "slokas/brahm jeev maya/Brahm Jeev Maya Kya Hai 20 [0eniqBNdBLU]/ramayan जाकी रही.mp3"
    ],
    "बिदुषन्ह": [
        "slokas/brahm jeev maya/Brahm Jeev Maya Kya Hai 20 [0eniqBNdBLU]/ramayan बिदुषन्ह.mp3"
    ],
    "आनन्द सिन्धु": [
        "slokas/brahm jeev maya/Brahm Jeev Maya Kya Hai 20 [0eniqBNdBLU]/ramayan आनन्द सिन्धु.mp3"
    ],
    "छिति जल": [
        "slokas/brahm jeev maya/Brahm Jeev Maya Kya Hai 18 [J89Yz68wx0Q]/ramayan छिति जल.mp3"
    ],
    "रामचंद्र के भजन": [
        "slokas/brahm jeev maya/Brahm Jeev Maya Kya Hai 21 [C569Zsez-OA]/ramayan रामचंद्र के भजन.mp3"
    ],
    "रमा समेत": [
        "slokas/brahm jeev maya/Brahm Jeev Maya Kya Hai 21 [C569Zsez-OA]/ramayan रमा समेत.mp3"
    ],
    "सिव बिरंचि": [
        "slokas/brahm jeev maya/Brahm Jeev Maya Kya Hai 21 [C569Zsez-OA]/ramayan सिव बिरंचि.mp3"
    ],
    "ते सठ महासिंधु बिनु": [
        "slokas/brahm jeev maya/Brahm Jeev Maya Kya Hai 21 [C569Zsez-OA]/ramayan ते सठ महासिंधु बिनु.mp3"
    ],
    "जीव कि ईस": [
        "slokas/brahm jeev maya/Brahm Jeev Maya Kya Hai 21 [C569Zsez-OA]/ramayan जीव कि ईस.mp3"
    ],
    "ताते नास": [
        "slokas/brahm jeev maya/Brahm Jeev Maya Kya Hai 21 [C569Zsez-OA]/ramayan ताते नास.mp3"
    ],
    "सिव चतुरानन": [
        "slokas/brahm jeev maya/Brahm Jeev Maya Kya Hai 21 [C569Zsez-OA]/ramayan सिव चतुरानन.mp3"
    ],
    "सोई सुख": [
        "slokas/brahm jeev maya/Brahm Jeev Maya Kya Hai 21 [C569Zsez-OA]/ramayan सोई सुख.mp3"
    ],
    "जग पेखन सब": [
        "slokas/brahm jeev maya/Brahm Jeev Maya Kya Hai 21 [C569Zsez-OA]/ramayan जग पेखन सब.mp3"
    ],
    "नारद भव बिरंचि": [
        "slokas/brahm jeev maya/Brahm Jeev Maya Kya Hai 21 [C569Zsez-OA]/ramayan नारद भव बिरंचि.mp3"
    ],
    "ते कामधेनु": [
        "slokas/brahm jeev maya/Brahm Jeev Maya Kya Hai 21 [C569Zsez-OA]/ramayan ते कामधेनु.mp3"
    ]
}