{
    "": [
        "slokas/brahm jeev maya/Brahm Jeev Maya Kya Hai 03 [aSekNB0qHSY]/शंकराचार्य.mp3",
        "slokas/brahm jeev maya/Brahm Jeev Maya Kya Hai 03 [aSekNB0qHSY]/शंकराचार्य_2.mp3",
        "slokas/brahm jeev maya/Brahm Jeev Maya Kya Hai 16 [ei6Z8RaB2N0]/शंकराचार्य.mp3"
    ],
    "द्विविधं हि ब्रह्म अवगम्यते": [
        "slokas/brahm jeev maya/Brahm Jeev Maya Kya Hai 03 [aSekNB0qHSY]/शंकराचार्य द्विविधं हि ब्रह्म अवगम्यते.mp3",
        "slokas/brahm jeev maya/Brahm Jeev Maya Kya Hai 07 [ltugKF0RE7w]/शंकराचार्य द्विविधं हि ब्रह्म अवगम्यते.mp3"
    ],
    "मूर्तं चैवामूर्तं द्वे एव": [
        "slokas/brahm jeev maya/Brahm Jeev Maya Kya Hai 03 [aSekNB0qHSY]/शंकराचार्य मूर्तं चैवामूर्तं द्वे एव.mp3",
        "slokas/brahm jeev maya/Brahm Jeev Maya Kya Hai 07 [ltugKF0RE7w]/शंकराचार्य मूर्तं चैवामूर्तं द्वे एव.mp3"
    ],
    "नाथेतिश्रुतयो न": [
        "slokas/brahm jeev maya/Brahm Jeev Maya Kya Hai 22 [Kot3Rv9_U-E]/शंकराचार्य नाथेतिश्रुतयो न.mp3"
    ],
    "अतो भेदाभेदावग": [
        "slokas/brahm jeev maya/Brahm Jeev Maya Kya Hai 04 [BCOGNSVq71s]/शंकराचार्य अतो भेदाभेदावग.mp3"
    ],
    "श्रद्धाभक्त्योरभावेऽपि": [
        "slokas/brahm jeev maya/Brahm Jeev Maya Kay Hai 33 [EdMKkh36OJo]/शंकराचार्य श्रद्धाभक्त्योरभावेऽपि.mp3",
        "slokas/brahm jeev maya/Brahm Jeev Maya Kya Hai 07 [ltugKF0RE7w]/शंकराचार्य श्रद्धाभक्त्योरभावेऽपि.mp3"
    ],
    "काम्योपासनयार्थयन्त्यनुदिनं": [
        "slokas/brahm jeev maya/Brahm Jeev Maya Kya Hai 19 [E3pTYnVJV8I]/शंकराचार्य काम्योपासनयार्थयन्त्यनुदिनं.mp3"
    ],
    "ब्रह्माण्डानि": [
        "slokas/brahm jeev maya/Brahm Jeev Maya Kya Hai 19 [E3pTYnVJV8I]/शंकराचार्य ब्रह्माण्डानि.mp3"
    ],
    "द्वौ भक्तौ": [
        "slokas/brahm jeev maya/Brahm Jeev Maya Kya Hai 19 [E3pTYnVJV8I]/शंकराचार्य द्वौ भक्तौ.mp3"
    ],
    "आरूढ": [
        "slokas/brahm jeev maya/Brahm Jeev Maya Kya Hai 17 [zAt0Ets2FII]/शंकराचार्य आरूढ.mp3",
        "slokas/brahm jeev maya/Brahm Jeev Maya Kya Hai 18 [J89Yz68wx0Q]/शंकराचार्य आरूढ.mp3",
        "slokas/brahm jeev maya/Brahm Jeev Maya Kya Hai 19 [E3pTYnVJV8I]/शंकराचार्य आरूढ.mp3"
    ],
    "नारायण करुणामय": [
        "slokas/brahm jeev maya/Brahm Jeev Maya Kya Hai 23 [eFM0-7cUEZk]/शंकराचार्य नारायण करुणामय.mp3"
    ],
    "भक्त्यैकगम्योभवमुक्तिहेतुः": [
        "slokas/brahm jeev maya/Brahm Jeev Maya Kya Hai 23 [eFM0-7cUEZk]/शंकराचार्य भक्त्यैकगम्योभवमुक्तिहेतुः.mp3"
    ],
    "भूतदयां विस्तारय": [
        "slokas/brahm jeev maya/Brahm Jeev Maya Kya Hai 23 [eFM0-7cUEZk]/शंकराचार्य भूतदयां विस्तारय.mp3"
    ],
    "हृदं भोजे कृष्णा": [
        "slokas/brahm jeev maya/Brahm Jeev Maya Kya Hai 23 [eFM0-7cUEZk]/शंकराचार्य हृदं भोजे कृष्णा.mp3"
    ],
    "भज गोविन्दम": [
        "slokas/brahm jeev maya/Brahm Jeev Maya Kya Hai 16 [ei6Z8RaB2N0]/शंकराचार्य भज गोविन्दम.mp3"
    ],
    "निर्गुण वाक्यानां": [
        "slokas/brahm jeev maya/Brahm Jeev Maya Kya Hai 21 [C569Zsez-OA]/शंकराचार्य निर्गुण वाक्यानां.mp3"
    ],
    "मनुष्यत्वं मुमुक्षुत्वं": [
        "slokas/brahm jeev maya/Brahm Jeev Maya Kya Hai 01 [U7uyPSCJZbI]/शंकराचार्य मनुष्यत्वं मुमुक्षुत्वं.mp3"
    ],
    "दुर्लभं त्रयमेवैतत् देवानुग्रह": [
        "slokas/brahm jeev maya/Brahm Jeev Maya Kya Hai 01 [U7uyPSCJZbI]/शंकराचार्य दुर्लभं त्रयमेवैतत् देवानुग्रह.mp3"
    ],
    "पुनरपि जननं पुन": [
        "slokas/brahm jeev maya/Brahm Jeev Maya Kya Hai 05 [PeR4gFlRZLA]/शंकराचार्य पुनरपि जननं पुन.mp3"
    ],
    "द्विविधं हि ब्रह्म": [
        "slokas/brahm jeev maya/Brahm Jeev Maya Kya Hai 35 [FuIzJo-0ohw]/शंकराचार्य द्विविधं हि ब्रह्म.mp3"
    ],
    "मूर्तं चैवामूर्तं": [
        "slokas/brahm jeev maya/Brahm Jeev Maya Kya Hai 35 [FuIzJo-0ohw]/शंकराचार्य मूर्तं चैवामूर्तं.mp3"
    ]
}